enerhabitat/__init__.py
enerhabitat/ehtools.py
enerhabitat-0.1.12.dist-info/METADATA
enerhabitat-0.1.12.dist-info/WHEEL
enerhabitat-0.1.12.dist-info/licenses/LICENSE
enerhabitat-0.1.12.dist-info/RECORD
