Metadata-Version: 2.4
Name: enerhabitat
Version: 0.1.12
Summary: Paquete instalable para EnerHabitat
Project-URL: Homepage, https://github.com/AltamarMx/eh_development
Project-URL: Issues, https://github.com/AltamarMx/eh_development
Author-email: Guillermo Barrios del Valle <gbv@ier.unam.mx>, Fernando Rodriguez Calderon <ferrodriguez2509@gmail.com>
License-Expression: MIT
License-File: LICENSE
Classifier: Intended Audience :: Education
Classifier: Intended Audience :: Science/Research
Classifier: License :: OSI Approved :: MIT License
Classifier: Operating System :: OS Independent
Classifier: Programming Language :: Python
Classifier: Programming Language :: Python :: 3.9
Classifier: Programming Language :: Python :: 3.10
Classifier: Programming Language :: Python :: 3.11
Classifier: Programming Language :: Python :: 3.12
Classifier: Programming Language :: Python :: 3.13
Classifier: Topic :: Education :: Testing
Classifier: Topic :: Scientific/Engineering :: Atmospheric Science
Classifier: Topic :: Software Development :: Libraries :: Python Modules
Requires-Python: >=3.9
Requires-Dist: numba>=0.60.0
Requires-Dist: pvlib>=0.12.0
